ramps_superb/__init__.py
ramps_superb/status_1.py
ramps_superb/_clique/__init__.py
ramps_superb/_clique/group/__init__.py
ramps_superb/_licenses/gpl-3.0-standalone.html
ramps_superb/_status/status.proc.py
ramps_superb/_status/vows/1/status_1.py
ramps_superb/charts/VLOCH.py
ramps_superb/charts/superb_line.py
ramps_superb/charts/trend_side_circles.py
ramps_superb/furniture/DF/reverse.py
ramps_superb/victory_percentage/holding.py
ramps_superb-0.0.2.dist-info/METADATA
ramps_superb-0.0.2.dist-info/WHEEL
ramps_superb-0.0.2.dist-info/top_level.txt
ramps_superb-0.0.2.dist-info/RECORD
