Metadata-Version: 2.1
Name: ramps_superb
Version: 0.0.2
License: 
Requires-Dist: bracelet
Requires-Dist: click
Requires-Dist: pandas
Requires-Dist: plotly
Requires-Dist: rich
